mcp_chat_analysis/embeddings.py
mcp_chat_analysis/models.py
mcp_chat_analysis/processors.py
mcp_chat_analysis/server.py
mseep_mcp_server_chat_analysis-0.1.4.dist-info/METADATA
mseep_mcp_server_chat_analysis-0.1.4.dist-info/WHEEL
mseep_mcp_server_chat_analysis-0.1.4.dist-info/entry_points.txt
mseep_mcp_server_chat_analysis-0.1.4.dist-info/licenses/LICENSE
mseep_mcp_server_chat_analysis-0.1.4.dist-info/RECORD
