Metadata-Version: 2.4
Name: mseep-mcp-server-chat-analysis
Version: 0.1.4
Summary: MCP server for chat analysis using vector embeddings and knowledge graphs
Project-URL: Homepage, https://github.com/yourusername/mcp-server-chat-analysis
Project-URL: Documentation, https://github.com/yourusername/mcp-server-chat-analysis#readme
Project-URL: Repository, https://github.com/yourusername/mcp-server-chat-analysis.git
Project-URL: Issues, https://github.com/yourusername/mcp-server-chat-analysis/issues
Author-email: mseep <support@skydeck.ai>
License: MIT License
License-File: LICENSE
Keywords: analysis,chat,knowledge-graph,mcp,vector
Classifier: Development Status :: 3 - Alpha
Classifier: Intended Audience :: Developers
Classifier: License :: OSI Approved :: MIT License
Classifier: Programming Language :: Python :: 3
Classifier: Programming Language :: Python :: 3.8
Classifier: Programming Language :: Python :: 3.9
Classifier: Programming Language :: Python :: 3.10
Classifier: Topic :: Scientific/Engineering :: Artificial Intelligence
Classifier: Topic :: Text Processing :: General
Requires-Python: >=3.8
Requires-Dist: modelcontextprotocol>=0.1.0
Requires-Dist: neo4j>=5.15.0
Requires-Dist: pydantic>=2.5.0
Requires-Dist: python-dotenv>=1.0.0
Requires-Dist: qdrant-client>=1.7.0
Requires-Dist: sentence-transformers>=2.2.2
Provides-Extra: dev
Requires-Dist: black>=23.0; extra == 'dev'
Requires-Dist: flake8>=6.0; extra == 'dev'
Requires-Dist: mypy>=1.0; extra == 'dev'
Requires-Dist: pytest-asyncio>=0.21.0; extra == 'dev'
Requires-Dist: pytest>=7.0; extra == 'dev'
